<?xml version="1.0" encoding="UTF-8"?>
<!DOCTYPE task-wr PUBLIC "-//WindRiver.com//DTD DITA 1.2 Wind River General Task//EN" "task-wr.dtd">
<task-wr domains="(topic task task-wr)                            (topic hi-d)                            (topic pr-d)                            (topic sw-d)                            (topic ui-d)                            (topic wr-sw-d)                            (topic xml-d)   " id="jow1408735356648" xml:lang="en-us" xmlns:ditaarch="http://dita.oasis-open.org/architecture/2005/">
<!-- Modification History
        
-->
    <title ixia_locid="1">Creating a Volume</title>
    <shortdesc ixia_locid="2">Before you can use an image, you must create a
            <nameliteral ixia_locid="32">Cinder</nameliteral> volume for it.</shortdesc>
    <prolog>
        <author ixia_locid="3">MichaelB</author>
    </prolog>
    <taskbody>
        <context id="context_N1001F_N1001C_N10001" ixia_locid="4"/>
        <steps>
            <step id="step_N10026_N10023_N1001C_N10001" ixia_locid="5">
                <cmd ixia_locid="6">List the set of volumes currently available on the system.</cmd>
                <info ixia_locid="7">
                    <p ixia_locid="8">Select <uicontrol ixia_locid="9">Volumes</uicontrol> in the <wintitle ixia_locid="10">Manage
                            Compute</wintitle> section of the <uicontrol ixia_locid="11">Project</uicontrol> tab to
                        open the <wintitle ixia_locid="12">Volumes</wintitle> page.</p>
                    <p ixia_locid="13">Since no volumes have been created yet, the list is empty as illustrated.</p>
                    <fig id="fig_dkw_p1l_2p" ixia_locid="14">
                        <image href="jow1408735695567.image" id="image_k4p_q1l_2p" ixia_locid="15" placement="inline" width="6in"/>
                    </fig>
                </info>
            </step>
            <step id="step_N1005C_N10023_N1001C_N10001" ixia_locid="17">
                <cmd ixia_locid="18">Configure the volume.</cmd>
                <info ixia_locid="19">
                    <p ixia_locid="20">On the <uicontrol ixia_locid="21">Volumes</uicontrol> page, click <uicontrol ixia_locid="22">Create
                            Volume</uicontrol> to display the <wintitle ixia_locid="23">Create Volume</wintitle>
                        window. Fill in the information as illustrated below.</p>
                    <fig id="fig_gpm_pbl_2p" ixia_locid="24">
                        <image href="jow1408736051023.image" id="image_gpx_pbl_2p" ixia_locid="25" placement="inline" width="5in"/>
                    </fig>
                </info>
            </step>
        </steps>
        <result id="result_N10089_N1001C_N10001" ixia_locid="27">
            <p ixia_locid="28">The new volume is added to the <wintitle ixia_locid="29">Volumes</wintitle> list.</p>
            <fig id="fig_onc_kcl_2p" ixia_locid="30">
                <image href="jow1408736486389.image" id="image_d2b_lcl_2p" ixia_locid="31" placement="inline" width="6in"/>
            </fig>
        </result>
        <postreq id="postreq_N100BC_N10024_N10001" ixia_locid="33">
            <note id="note_N100C0_N100BC_N10024_N10001" ixia_locid="34">
                <p ixia_locid="35">To complete the deployment scenarios, this task must be repeated as<nameliteral ixia_locid="36">
                        user2</nameliteral>, substituting appropriate names as described in <xref href="jow1404333809139.xml" ixia_locid="37"/>.</p>
            </note>
        </postreq>
    </taskbody>
</task-wr>