<?xml version="1.0" encoding="UTF-8"?>
<!DOCTYPE task-wr PUBLIC "-//WindRiver.com//DTD DITA 1.2 Wind River General Task//EN" "task-wr.dtd">
<task-wr id="jow1429811350849" xml:lang="en-us">
<!-- Modification History
        
-->
    <title id="1">Creating and Using Memory Profiles</title>
    <shortdesc id="2">You can optionally save the huge pages configuration for a host as a profile, and
        apply the profile to other hosts.</shortdesc>
    <prolog>
        <author id="3">Jim Owens</author>
    </prolog>
    <taskbody>
        <context id="context_N1001F_N1001C_N10001" id="4">
            <p id="5">For more information about huge page configurations, see <xref href="jow1423087781001.xml" id="6"/>.</p>
            <p id="26">As an alternative to the web administration interface, you can use the following CLI
                command to create a memory profile:</p>
            <codeblock id="27"><systemoutput id="28">~(keystone-admin)$ </systemoutput><userinput id="29">system memprofile-add <varname id="30">memoryprofile</varname> <varname id="31">hostid</varname></userinput></codeblock>
            <p id="32">where <varname id="33">memoryprofile</varname> is the name or UUID of the memory profile, and
                    <varname id="34">hostid</varname> is the name or UUID of the host from which to create
                the profile.</p>
        </context>
        <steps>
            <step conref="jow1426453628262.xml#jow1426453628262/step_N1002B_N10028_N1001C_N10001" id="step_N1002F_N1002C_N1001C_N10001" id="7">
                <cmd id="8"/>
            </step>
            <step id="step_N10038_N1002C_N1001C_N10001" id="9">
                <cmd id="10">On the Memory tab, click <uicontrol id="11">Create Memory Profile</uicontrol>.</cmd>
                <info id="12">
                    <p id="13">The <wintitle id="14">Create Memory Profile</wintitle> dialog box appears.</p>
                    <fig id="fig_cj1_byq_5r" id="15">
                        <image href="jow1429812100638.image" id="image_bk3_byq_5r" id="16" width="4in">
                            <alt id="17">Create Memory Profile</alt>
                        </image>
                    </fig>
                </info>
            </step>
            <step id="step_N10062_N1002C_N1001C_N10001" id="18">
                <cmd id="19">Type a name for the memory profile.</cmd>
            </step>
            <step id="step_N1006B_N1002C_N1001C_N10001" id="20">
                <cmd id="21">Click <uicontrol id="22">Create Memory
                        Profile</uicontrol> to save the profile and close the dialog box.</cmd>
            </step>
        </steps>
        <result id="result_N10075_N1001C_N10001" id="23">
            <p id="24">You can apply this profile to other hosts by editing the host
                settings in the web administration interface. For information about editing a host,
                see <xref href="jow1404333790046.xml" id="25"/>. You can also use the
                following CLI command to apply a memory profile to a host:</p>
            <codeblock id="35"><systemoutput id="36">~(keystone-admin)$ </systemoutput><userinput id="37">system host-apply-memprofile <varname id="38">memoryprofile</varname> <varname id="39">hostid</varname></userinput></codeblock>
            <p id="40">where <varname id="41">memoryprofile</varname> is the name or UUID of the memory profile, and
                    <varname id="42">hostid</varname> is the name or UUID of the host.</p>
            <p id="43">To manage memory profiles, you can use the <wintitle id="44">Memory Profiles</wintitle> tab
                on the <wintitle id="45">System Inventory</wintitle> page, or you can use the following CLI
                commands:</p>
            <ul id="ul_x1x_plr_5r">
                <li id="46">
                    <p id="47">To list memory profiles:</p>
                    <codeblock id="48"><systemoutput id="49">~(keystone-admin)$ </systemoutput><userinput id="50">system memprofile-list</userinput></codeblock>
                </li>
                <li id="51">
                    <p id="52">To show details for a memory profile:</p>
                    <codeblock id="53"><systemoutput id="54">~(keystone-admin)$ </systemoutput><userinput id="55">system memprofile-show <varname id="56">memoryprofile</varname></userinput></codeblock>
                    <p id="57">where <varname id="58">memoryprofile</varname> is the name or UUID of the memory
                        profile.</p>
                </li>
                <li id="59">
                    <p id="60">To delete a memory profile:</p>
                    <codeblock id="61"><systemoutput id="62">~(keystone-admin)$ </systemoutput><userinput id="63">system memprofile-delete <varname id="64">memoryprofile</varname></userinput></codeblock>
                    <p id="65">where <varname id="66">memoryprofile</varname> is the name or UUID of the memory
                        profile.</p>
                </li>
            </ul>
        </result>
    </taskbody>
</task-wr>